{"res": [{"lists": [{"title": "41年:罗马帝国第三任皇帝卡利古拉被近卫军大队长刺杀身亡，其叔父克劳狄一世被拥立为新皇帝。", "year": "41"}, {"title": "1038年:中国山西定襄 — 忻州一带发生7.25级地震，造成37,908人伤亡，太原悬瓮寺遭到毁坏而废弃。", "year": "1038"}, {"title": "1076年:教宗额我略七世被亨利四世废黜。", "year": "1076"}, {"title": "1118年:格拉修二世任第162任教宗。", "year": "1118"}, {"title": "1458年:年仅14岁的马加什一世被选为匈牙利国王，其任内匈牙利王国国力达到颠峰。", "year": "1458"}, {"title": "1601年:利玛窦来到中国北京传播基督教。", "year": "1601"}, {"title": "1679年:英格兰国王查理二世解散议会。", "year": "1679"}, {"title": "1742年:查理七世成为神圣罗马帝国皇帝。", "year": "1742"}, {"title": "1848年:美国木匠詹姆斯·马歇尔于加州科洛马发现天然金块，引发淘金潮。", "year": "1848"}, {"title": "1859年:瓦拉几亚和摩尔达维亚两个公国合并为罗马尼亚联合公国，附属于奥斯曼帝国之下。", "year": "1859"}, {"title": "1888年:雅克布·L·沃特曼得到打字机色带的专利。", "year": "1888"}, {"title": "1891年:约翰·巴兰斯任新西兰总理。", "year": "1891"}, {"title": "1907年:罗伯特·贝登堡发起童军运动。", "year": "1907"}, {"title": "1914年:张裕公司生产的葡萄酒正式注册，商标为“双麒麟牌”。", "year": "1914"}, {"title": "1922年:（Christian Kent Nelson）取得的专利。", "year": "1922"}, {"title": "1924年:黄埔军校开始筹建。", "year": "1924"}, {"title": "1924年:弗拉基米尔·列宁逝世后，苏联政府将彼得大帝建造的彼得格勒改名为“列宁格勒”。", "year": "1924"}, {"title": "1936年:张国焘在共产国际的压力下取消“中国共产党中央委员会”，追随中央红军北上。", "year": "1936"}, {"title": "1936年:阿尔贝特·萨罗就任第113届法国总理。", "year": "1936"}, {"title": "1943年:第二次世界大战:富兰克林·德拉诺·罗斯福和温斯顿·丘吉尔结束卡萨布兰卡会议。", "year": "1943"}, {"title": "1946年:联合国大会第一次会议召开，并通过有关原子能和平利用的决议。", "year": "1946"}, {"title": "1958年:英美科学家完成核聚变试验。", "year": "1958"}, {"title": "1961年:一架载有两枚核弹的B-52轰炸机在北卡罗莱那州戈尔兹伯勒空中解体。", "year": "1961"}, {"title": "1962年:布莱恩·爱普斯坦担任披头士乐队经理人。", "year": "1962"}, {"title": "1966年:印度航空101号班机（波音707）在法国和意大利交界处的勃朗峰坠毁，机上117人全部遇难。", "year": "1966"}, {"title": "1966年:英迪拉·甘地任印度总理。", "year": "1966"}, {"title": "1972年:二战时的日本士兵横井庄一在关岛被人发现，此前他已经在丛林里过了24年。", "year": "1972"}, {"title": "1978年:一苏联携带核能发电机的间谍卫星坠落于加拿大。", "year": "1978"}, {"title": "1984年:美国苹果公司发布继Lisa之后的第二部图形用户界面电脑麦金塔电脑。", "year": "1984"}, {"title": "1984年:邓小平视察深圳经济特区，并为经济特区提词。", "year": "1984"}, {"title": "1986年:美国国家航空航天局发射的旅行者2号探测器成为首个掠过天王星的太空探测器。", "year": "1986"}, {"title": "1989年:马来西亚首相马哈迪·莫哈末因胸口疼痛，而在吉隆坡中央医院接受心脏绕道手术。", "year": "1989"}, {"title": "1989年:连环杀手泰德·邦迪在佛罗里达被送上电椅。", "year": "1989"}, {"title": "1990年:安徽省安庆港区江面浓雾，“大庆407”油轮与安徽省池州行署东至县大渡口区杨桥乡杨套村“东至挂114”客渡轮相撞，80人死亡、32人失踪、“东至挂114”客渡轮沉没。", "year": "1990"}, {"title": "1992年:中华人民共和国与以色列国建立大使级外交关系。", "year": "1992"}, {"title": "1995年:OJ·辛普森涉嫌杀妻案正式开庭审理。", "year": "1995"}, {"title": "2003年:美国国土安全部正式运作。", "year": "2003"}, {"title": "2006年:BenQ与西门子合并后，第一支双品牌手机S88在台湾正式上市。", "year": "2006"}, {"title": "2016年:寒流席卷北半球多国，位处市区的尖沙咀香港天文台总部于当日下午3时40分录得摄氏3.1度的低温，是1957年以来录得的最低气温，也创下自1885年有纪录以来全年第3低温纪录。澳门在当日下午2时15分录得摄氏1.6度的低温，是1949年以来的1月最低气温。台湾中央气象局则于当日早上5:30与7:15在台北测站测得摄氏4度的低温，是1972年来录得的最低气温。", "year": "2016"}, {"title": "2022年:美国国家航空航天局的红外线太空望远镜詹姆斯·韦伯太空望远镜成功抵达最终观测位置晕轮轨道拉格朗日L2点运行。", "year": "2022"}], "name": "大事记", "id": "1"}, {"lists": [{"title": "76年:哈德良，罗马皇帝（138年逝世）", "year": "76"}, {"title": "1712年:腓特烈二世，普鲁士国王（1786年逝世）", "year": "1712"}, {"title": "1732年:博马舍，法国喜剧作家（1799年逝世）", "year": "1732"}, {"title": "1848年:苏里科夫，俄罗斯画家（1916年逝世）", "year": "1848"}, {"title": "1862年:伊迪丝·沃顿，美国女作家（1937年逝世）", "year": "1862"}, {"title": "1869年:白川义则，1932年攻占上海日陆军总司令（1932年逝世）", "year": "1869"}, {"title": "1880年:尤塔，黑山王国王储妃（1946年逝世）", "year": "1880"}, {"title": "1891年:瓦尔特·莫德尔，德国陆军元帅（1945年逝世）", "year": "1891"}, {"title": "1898年:黄公略，中国工农红军高级将领（1931年逝世）", "year": "1898"}, {"title": "1904年:小泉纯也，日本政治家、小泉纯一郎的父亲（1969年逝世）", "year": "1904"}, {"title": "1921年:王永在，台塑集团共同创办人、王永庆的弟弟 (2014年逝世)", "year": "1921"}, {"title": "1930年:吴敬琏，中国经济学家", "year": "1930"}, {"title": "1934年:游效曾，中国化学家（2016年逝世）", "year": "1934"}, {"title": "1941年:尼尔·戴门，美国歌手", "year": "1941"}, {"title": "1942年:鹿野道彦，日本政治家，民主党众议院议员、农林水产大臣（2021年逝世）", "year": "1942"}, {"title": "1943年:莎伦·塔特，美国女演员（1969年逝世）", "year": "1943"}, {"title": "1947年:加来道雄，日裔美籍理论物理学家", "year": "1947"}, {"title": "1950年:翁倩玉，台湾女艺人", "year": "1950"}, {"title": "1951年:五轮真弓，日本女歌手", "year": "1951"}, {"title": "1953年:文在寅，韩国总统", "year": "1953"}, {"title": "1954年:宝咏琴，香港女性企业家（2003年逝世）", "year": "1954"}, {"title": "1957年:马克·伊顿，美国NBA篮球运动员（2021年逝世）", "year": "1957"}, {"title": "1957年:李维安，中国学者", "year": "1957"}, {"title": "1960年:梁智强，新加坡导演", "year": "1960"}, {"title": "1960年:林艺真，韩国女演员", "year": "1960"}, {"title": "1961年:娜妲莎·金斯基，德国女演员", "year": "1961"}, {"title": "1963年:岩井俊二，日本导演", "year": "1963"}, {"title": "1969年:柳好贞，韩国女演员", "year": "1969"}, {"title": "1971年:南佳也，日本AV男优", "year": "1971"}, {"title": "1971年:森下佳子，日本女编剧", "year": "1971"}, {"title": "1972年:翁金骅，香港篮球运动员、评述员", "year": "1972"}, {"title": "1977年:孟关良，中国皮划艇运动员", "year": "1977"}, {"title": "1979年:严屹宽，中国男演员", "year": "1979"}, {"title": "1982年:刘耿欣，台湾棒球选手", "year": "1982"}, {"title": "1982年:谢宛谕，新加坡华人女明星", "year": "1982"}, {"title": "1983年:文宝玲，韩国女演员", "year": "1983"}, {"title": "1984年:枢簗，日本漫画家", "year": "1984"}, {"title": "1984年:邹幸彤，香港大律师，现为支联会副主席", "year": "1984"}, {"title": "1985年:邓景煌，香港足球运动员", "year": "1985"}, {"title": "1985年:法比安娜·科劳迪诺，巴西女子排球运动员", "year": "1985"}, {"title": "1986年:美莎·芭顿，英国裔美国籍电影、电视、舞台女演员", "year": "1986"}, {"title": "1986年:刘倩婷，2009年度香港小姐竞选冠军", "year": "1986"}, {"title": "1987年:林育品，台湾女艺人", "year": "1987"}, {"title": "1989年:巩立姣，中国女子铅球运动员", "year": "1989"}, {"title": "1990年:入江陵介，日本游泳运动员", "year": "1990"}, {"title": "1990年:阿部真央，日本女创作歌手", "year": "1990"}, {"title": "1990年:金玟锡，韩国男演员", "year": "1990"}, {"title": "1991年:李雪芮，中国女子羽毛球运动员", "year": "1991"}, {"title": "1992年:冯薪朵，中国女团SNH48前成员", "year": "1992"}, {"title": "1993年:伊织萌，日本知名cosplayer、写真偶像、广播电台主持人", "year": "1993"}, {"title": "1994年:陈晓彤，香港女歌手", "year": "1994"}, {"title": "1994年:刘永才，韩国男子偶像团体B.A.P成员", "year": "1994"}, {"title": "1999年:妮基，印尼女歌手、词曲作家、唱片制作人", "year": "1999"}, {"title": "2000年:李寄旭，韩国男子偶像乐队ONEWE成员", "year": "2000"}, {"title": "2012年:雅典娜·玛格丽特·法兰西丝·玛丽，丹麦公主", "year": "2012"}, {"title": "生年不详:樋野茉理，日本漫画家", "year": "None"}], "name": "出生", "id": "2"}, {"lists": [{"title": "41年:卡利古拉，罗马皇帝（12年出生）", "year": "41"}, {"title": "1366年:阿方索四世，阿拉贡国王（1299年出生）", "year": "1366"}, {"title": "1622年:织田长益，日本幕府将军，织田信长的弟弟（1547年出生）", "year": "1622"}, {"title": "1632年:德川秀忠，日本幕府将军（1579年出生）", "year": "1632"}, {"title": "1935年:黄节，中国诗人、历史学家（1873年出生）", "year": "1935"}, {"title": "1938年:韩复榘，中国军官，抗战初期因违令撤退被被枪毙（1890年出生）", "year": "1938"}, {"title": "1960年:埃德温·费歇尔，钢琴家（1886年出生）", "year": "1960"}, {"title": "1964年:邱善佑，槟城殷商和政治家（1886年出生）", "year": "1964"}, {"title": "1965年:温斯顿·丘吉尔，英国首相（1874年出生）", "year": "1965"}, {"title": "1966年:霍米·巴巴，印度核物理学家（1909年出生）", "year": "1966"}, {"title": "1973年:，演员（1896年出生）", "year": "1973"}, {"title": "1983年:刘克宣，香港演员（1904年出生）", "year": "1983"}, {"title": "2011年:罗兆辉，香港传奇商人（1964年出生）", "year": "2011"}, {"title": "2012年:泰奥·安哲罗普洛斯，希腊导演、编剧（1935年出生）", "year": "2012"}, {"title": "2012年:阮品强，香港民主党创党党员（1943年出生）", "year": "2012"}, {"title": "2015年:奥托·卡利乌斯，二次大战德国战车指挥官（1922年出生）", "year": "2015"}, {"title": "2016年:马文·闵斯基，美国科学家（1927年出生）", "year": "2016"}, {"title": "2022年:谢尔顿·席佛，美国政治人物（1944年出生）", "year": "2022"}, {"title": "2022年:米里亚姆·诺尔，以色列法学家（1947年出生）", "year": "2022"}, {"title": "2022年:乔拉尼·西尔韦斯特，匈牙利男子竞技体操运动员（1970年出生）", "year": "2022"}], "name": "逝世", "id": "3"}], "month": 1, "day": 24}