{"res": [{"lists": [{"title": "1815年:拿破仑·波拿巴逃离被流放的厄尔巴岛，其后回到法国建立百日王朝。", "year": "1815"}, {"title": "1871年:普法战争以法国失败告终。", "year": "1871"}, {"title": "1876年:日本胁迫朝鲜缔结《江华条约》。", "year": "1876"}, {"title": "1917年:德国宣布全面实施无限制潜艇战，美国与德国断交。", "year": "1917"}, {"title": "1918年:香港跑马地马场大火。", "year": "1918"}, {"title": "1935年:英国物理学家沃森瓦特首次演示他发明的雷达装置。", "year": "1935"}, {"title": "1936年:德国大众甲壳虫问世。", "year": "1936"}, {"title": "1936年:日本陆军1400多名青年军官发动军事政变，4天后以失败告终，史称二二六兵变。", "year": "1936"}, {"title": "1945年:第二次世界大战:大阪大空袭。", "year": "1945"}, {"title": "1952年:温斯顿·丘吉尔宣布英国已经拥有原子弹。", "year": "1952"}, {"title": "1952年:文森特·梅西宣誓成为加拿大首位本土出生的总督。", "year": "1952"}, {"title": "1980年:以色列与埃及恢复正常外交关系后互派大使。", "year": "1980"}, {"title": "1989年:中国南极中山站在拉斯曼丘陵海滨落成。", "year": "1989"}, {"title": "1991年:伊拉克总统萨达姆·侯赛因宣布从科威特撤军。", "year": "1991"}, {"title": "1993年:美国纽约世界贸易中心被伊斯兰恐怖组织在地下室放置炸弹并引发爆炸，导致6人死亡，1000多人受伤。", "year": "1993"}, {"title": "1995年:英国巴林银行宣布破产，其原因是该银行交易员尼克·李森的违规交易，导致银行损失14亿美元。", "year": "1995"}, {"title": "2001年:阿富汗塔利班政权摧毁巴米扬大佛。", "year": "2001"}, {"title": "2005年:日本自行研制的H-IIA运载火箭搭载一颗多功能卫星在鹿儿岛县种子岛宇宙中心发射升空。", "year": "2005"}, {"title": "2005年:埃及总统胡赛尼·穆巴拉克宣布将修改宪法，允许多位候选人参选埃及总统。", "year": "2005"}, {"title": "2008年:纽约爱乐乐团在北朝鲜首都平壤举行音乐会，是北朝鲜建国60年来第一个演出的美国乐团。", "year": "2008"}, {"title": "2011年:联合国安理会所有成员国一致通过第1970号决议，对发生在利比亚的混乱局势表示严重关切。", "year": "2011"}, {"title": "2012年:台湾屏东县发生里氏规模6.4强震。", "year": "2012"}, {"title": "2013年:埃及卢克索发生热气球爆炸事件，造成19人死亡，包括9名香港游客。", "year": "2013"}, {"title": "2014年:明报总编辑刘进图受袭。", "year": "2014"}], "name": "大事记", "id": "1"}, {"lists": [{"title": "1802年:维克多·雨果，法国作家、诗人（逝于1885年）", "year": "1802"}, {"title": "1808年:奥诺雷·杜米埃，法国画家、雕塑家（逝于1879年）", "year": "1808"}, {"title": "1846年:布法罗·比尔，美国军人、美洲野牛猎手（逝于1917年）", "year": "1846"}, {"title": "1851年，有马新一，日本海军中将（逝于1909年）", "year": "1851"}, {"title": "1869年:娜杰日达·康斯坦丁诺芙娜·克鲁普斯卡娅，列宁妻子、俄国布尔什维克革命家、政治家（逝于1939年）", "year": "1869"}, {"title": "1896年:安德烈·日丹诺夫，苏联政治人物，苏联领袖斯大林亲信（逝于1948年）", "year": "1896"}, {"title": "1905年:杨靖宇，东北抗日联军领导人（逝于1940年）", "year": "1905"}, {"title": "1928年:阿里埃勒·沙龙，以色列政治家，第11任以色列总理（逝于2014年）", "year": "1928"}, {"title": "1944年:黄兴桂，香港体育主持人", "year": "1944"}, {"title": "1954年:雷杰普·塔伊普·艾尔多安，土耳其政治人物，现任总统", "year": "1954"}, {"title": "1955年:武上纯希，日本特摄编剧", "year": "1955"}, {"title": "1956年:桑田佳祐，日本歌手，乐团南方之星主唱", "year": "1956"}, {"title": "1964年:谭伟豪，香港政界人物", "year": "1964"}, {"title": "1964年:林育如，艺名龙眼，台湾歌手（逝于1989年）", "year": "1964"}, {"title": "1966年:曾佩仪，香港女性配音员", "year": "1966"}, {"title": "1969年:崎元仁，日本作曲家", "year": "1969"}, {"title": "1969年:王丹，中国六四事件学生领袖", "year": "1969"}, {"title": "1972年:黄品冠，马来西亚歌手，乐队无印良品成员", "year": "1972"}, {"title": "1973年:奥里·冈纳·索斯克亚，挪威职业足球运动员", "year": "1973"}, {"title": "1974年:塞巴斯蒂安·勒布，法国赛车手，9次世界拉力锦标赛年度总冠军", "year": "1974"}, {"title": "1981年:袁耀发，香港歌手", "year": "1981"}, {"title": "1980年:明道，台湾演员，团体183club成员", "year": "1980"}, {"title": "1980年:方力申，香港演员、歌手，前香港游泳队成员", "year": "1980"}, {"title": "1982年:李娜，中国网球手，2011年法国网球公开赛女单冠军", "year": "1982"}, {"title": "1983年:李卓庭，香港歌手", "year": "1983"}, {"title": "1984年:艾迪巴约，多哥足球运动员", "year": "1984"}, {"title": "1984年:贝兰·萨特，土耳其女演员", "year": "1984"}, {"title": "1985年:藤本美贵，日本女歌手，偶像团体早安少女组第六期成员", "year": "1985"}, {"title": "1985年:费兰度·路兰迪，西班牙足球运动员", "year": "1985"}, {"title": "1985年:加贺美早纪，日本女演员", "year": "1985"}, {"title": "1986年:克莉丝朵·凯儿，日本女歌手", "year": "1986"}, {"title": "1986年:泰莉莎·柏尔马，澳大利亚女演员", "year": "1986"}, {"title": "1986年:沈熙燮，韩国男演员", "year": "1986"}, {"title": "1986年:庄群施，马来西亚著名华裔影视女歌手，M-Girls成员之一", "year": "1986"}, {"title": "1987年:李治廷，马来西亚裔香港男演员", "year": "1987"}, {"title": "1988年:郭灏霆，香港单车运动员", "year": "1988"}, {"title": "1989年:徐恩雅，韩国女演员", "year": "1989"}, {"title": "1991年:凯特琳·利华娜兹，美国女子游泳运动员", "year": "1991"}, {"title": "1991年:李昌燮，韩国歌手、团体BTOB成员", "year": "1991"}, {"title": "1991年:李彩麟，韩国歌手、团体2NE1成员", "year": "1991"}, {"title": "1992年:篠崎爱，日本写真女星", "year": "1992"}, {"title": "1992年:，美国电视节目主持人、模特儿、2010年环球小姐得主", "year": "1992"}, {"title": "1993年:李宇琪，中国女子组合SNH48成员", "year": "1993"}, {"title": "1996年:陈盈燕，台湾歌手、女子团体A'N'D成员", "year": "1996"}], "name": "出生", "id": "2"}, {"lists": [{"title": "1841年:关天培，清朝抗英名将，战死于虎门", "year": "1841"}, {"title": "1936年:斋藤实，死于二二六事件。", "year": "1936"}, {"title": "1936年:高桥是清，死于二二六事件。", "year": "1936"}, {"title": "1936年:渡边锭太郎，死于二二六事件。", "year": "1936"}, {"title": "1969年:列维·艾希科尔，以色列首相。", "year": "1969"}, {"title": "1992年:张友渔，中国现代法学家", "year": "1992"}, {"title": "2001年:克劳德·艾尔伍德·香农，美国数学家、信息论的创始人", "year": "2001"}, {"title": "2003年:大象林旺，台湾家喻户晓的动物明星，于台北市立动物园病逝", "year": "2003"}, {"title": "2006年:，俄罗斯NTV记者，荣获2002年俄罗斯“最佳电视记者”称号，终年33岁", "year": "2006"}, {"title": "2008年:房道龙，香港电影明星成龙父亲，于养和医院病逝", "year": "2008"}, {"title": "2016年:陆以正，中华民国外交官，曾任驻奥地利、危地马拉及南非等国大使。", "year": "2016"}], "name": "逝世", "id": "3"}], "month": 2, "day": 26}