{"res": [{"lists": [{"title": "457年:君士坦丁堡长老为利奥一世加冕成为拜占庭皇帝，之后其统治东罗马帝国长达20年。", "year": "457"}, {"title": "1301年:卡纳芬的爱德华（后爱德华二世）被封为威尔士亲王，此后该头衔便成为王储继承人的专属头衔。", "year": "1301"}, {"title": "1313年:底哈都建立彬牙王国，宣称法理上继承了缅甸的蒲甘王国。", "year": "1313"}, {"title": "1497年:佛罗伦萨修士吉罗拉莫·萨佛纳罗拉的支持者们聚众烧毁大量的艺术品、化妆品和书籍，史称虚荣之火。", "year": "1497"}, {"title": "1783年:美国独立战争期间，法国与西班牙合力进行的直布罗陀包围战以失败告终。", "year": "1783"}, {"title": "1795年:美利坚合众国宪法第十一条修正案获得批准通过，并且推翻美国最高法院对奇泽姆诉佐治亚州案的判决结果。", "year": "1795"}, {"title": "1807年:拿破仑率领的法国军队和俄国、普鲁士等国组成的第四次反法同盟在东普鲁士相遇，埃劳战役爆发。", "year": "1807"}, {"title": "1854年:瑞士政府通过了建立苏黎世联邦理工学院的法案。", "year": "1854"}, {"title": "1898年:德雷福斯事件中，法国自然主义文学家埃米尔·左拉被指控诽谤罪，起因为先前他在报纸刊登指责法国政府迫害犹太军官德雷福斯。", "year": "1898"}, {"title": "1914年:中华民国财政部通过《国币条例》，将银圆定为全国统一货币。", "year": "1914"}, {"title": "1914年:英国喜剧演员查理·卓别林在电影《威尼斯儿童赛车》中首次饰演著名的“流浪汉”角色。", "year": "1914"}, {"title": "1923年:河南郑州京汉铁路工人大罢工。", "year": "1923"}, {"title": "1939年:中国国民党成立国防最高委员会，蒋介石为委员长。", "year": "1939"}, {"title": "1940年:华特·迪士尼的第二部动画长篇电影《木偶奇遇记》上映。", "year": "1940"}, {"title": "1947年:东北人民解放军牡丹江军排长杨子荣活捉当地匪首“座山雕”张乐山。", "year": "1947"}, {"title": "1951年:朝鲜战争期间，韩国陆军于韩国山清郡、咸阳郡屠杀705名涉嫌通共的平民。", "year": "1951"}, {"title": "1955年:中华人民共和国全国人民代表大会常务委员会改志愿兵役制为义务兵役制。", "year": "1955"}, {"title": "1957年:中华人民共和国与斯里兰卡建交。", "year": "1957"}, {"title": "1959年:《中苏经济合作协定》在苏联莫斯科签订。", "year": "1959"}, {"title": "1962年:美国政府宣布对古巴实施全面贸易禁运，成为现代实施时间最长的经济制裁。", "year": "1962"}, {"title": "1964年:披头士乐队抵达纽约作美国全国巡回演唱。", "year": "1964"}, {"title": "1974年:中美洲岛国格林纳达脱离英国，独立建国。", "year": "1974"}, {"title": "1977年:在中国共产党中央委员会主席华国锋的授意下，《人民日报》发表社论，公开提出两个凡是。", "year": "1977"}, {"title": "1979年:运载2600多名越南船民的货轮“天运号”驶入香港，在南丫岛水域停泊。", "year": "1979"}, {"title": "1981年:日本政府确定本日为“北方领土日”。", "year": "1981"}, {"title": "1982年:国际奥委会医学委员会公布第一批禁止使用的兴奋剂名单。", "year": "1982"}, {"title": "1984年:美国太空人布鲁斯·麦克坎德雷斯和罗伯特·斯图尔特完成人类首次不系绳的舱外活动。", "year": "1984"}, {"title": "1986年:海地总统让·克劳德·杜瓦利埃下台。", "year": "1986"}, {"title": "1991年:海地首位民选总统让-贝特朗·阿里斯蒂德宣誓就职", "year": "1991"}, {"title": "1992年:欧洲共同体12个成员国代表在荷兰东南部的马斯垂克签订旨在建立欧洲联盟的《马斯垂克条约》。", "year": "1992"}, {"title": "1996年:波兰总理因被指控为莫斯科间谍而辞职。", "year": "1996"}, {"title": "1997年:NeXT与苹果公司合并，导致其公司老板乔布斯回归至苹果公司并取代阿梅里奥。", "year": "1997"}, {"title": "1998年:第18届冬季奥运会在日本长野开幕。", "year": "1998"}, {"title": "1999年:在侯赛因·本·塔拉勒逝世后，其儿子阿卜杜拉二世继任成为约旦哈希姆王国国王。", "year": "1999"}, {"title": "2009年:马达加斯加反对派领导人拉乔利纳率领的反政府示威者在首都塔那那利佛遭到忠于总统拉瓦卢马纳纳的安全部队的开火，导致至少30人死亡。", "year": "2009"}, {"title": "2012年:在马尔代夫爆发警察叛变及持续数周的群众示威后，总统穆罕默德·纳希德宣布辞职。", "year": "2012"}, {"title": "2014年:第22届冬季奥运在俄罗斯索契开幕。", "year": "2014"}, {"title": "2016年:朝鲜成功发射地球观测卫星光明星4号，因使用弹道导弹技术而遭受各国谴责。", "year": "2016"}], "name": "大事记", "id": "1"}, {"lists": [{"title": "574年:圣德太子，日本飞鸟时代的政治改革家（621年逝世）", "year": "574"}, {"title": "1102年:玛蒂尔达皇后，英格兰王位竞争者（1141年逝世）", "year": "1102"}, {"title": "1478年:托马斯·莫尔，英国哲学家（1535年逝世）", "year": "1478"}, {"title": "1741年:约翰·菲斯利，德裔英国画家（1825年逝世）", "year": "1741"}, {"title": "1812年:查尔斯·狄更斯，英国作家（1870年逝世）", "year": "1812"}, {"title": "1867年:劳拉·英格斯·怀德，美国作家（1957年逝世）", "year": "1867"}, {"title": "1873年:托马斯·安德鲁斯，英国造船家 （1912年逝世）", "year": "1873"}, {"title": "1877年:戈弗雷·哈罗德·哈代，英国数学家（1947年逝世）", "year": "1877"}, {"title": "1885年:辛克莱·刘易斯， 英国作家（1951年逝世）", "year": "1885"}, {"title": "1906年:溥仪，中国清朝末代皇帝（1967年逝世）", "year": "1906"}, {"title": "1906年:奥列格·安东诺夫，苏联飞机设计师（1984年逝世）", "year": "1906"}, {"title": "1910年:夏鼐，中国考古学家（1985年逝世）", "year": "1910"}, {"title": "1919年:德斯蒙德·多斯，美国陆军下士（2006年逝世）", "year": "1919"}, {"title": "1920年:王安，华裔美国电脑科学家（1990年逝世）", "year": "1920"}, {"title": "1929年:萨尔塔杰·阿齐兹，巴基斯坦政治人物和经济学家", "year": "1929"}, {"title": "1932年:阿尔弗莱德·沃尔登，美国宇航员（2020年逝世）", "year": "1932"}, {"title": "1934年:金美龄，台湾独立运动成员", "year": "1934"}, {"title": "1939年:哈尔莫科，印尼政治家（2021年逝世）", "year": "1939"}, {"title": "1940年:陈庆炎，新加坡第7任总统", "year": "1940"}, {"title": "1946年:皮特·波斯尔思韦特，英国演员（2011年逝世）", "year": "1946"}, {"title": "1952年:刘永，香港男演员", "year": "1952"}, {"title": "1954年:迪特·金特·波伦，德国歌手", "year": "1954"}, {"title": "1960年:詹姆斯·斯派德，美国演员", "year": "1960"}, {"title": "1965年:克里斯·洛克，美国喜剧演员、编剧、导演、监制", "year": "1965"}, {"title": "1966年:张世，台湾演员", "year": "1966"}, {"title": "1966年:陶君行，香港政界人物", "year": "1966"}, {"title": "1968年:张敏，香港女演员", "year": "1968"}, {"title": "1968年:洪莉娜，韩国女演员", "year": "1968"}, {"title": "1970年:张宏艳，香港女主播", "year": "1970"}, {"title": "1971年:阿妮塔·崔，朝鲜裔俄罗斯歌手", "year": "1971"}, {"title": "1972年:闫学晶，中国女演员", "year": "1972"}, {"title": "1973年:园崎未惠，日本女性[声优", "year": "1973"}, {"title": "1974年:史蒂夫·纳什，加拿大篮球运动员", "year": "1974"}, {"title": "1974年:Nujabes，日本唱片制作人、DJ、作曲家、编曲家、音乐制作人（2010年逝世）", "year": "1974"}, {"title": "1975年:刘绰琪，香港电视节目主持人、演员", "year": "1975"}, {"title": "1975年:陈俊杰，台湾网络红人（2019年逝世）", "year": "1975"}, {"title": "1978年:郑亨敦，韩国搞笑艺人、主持人", "year": "1978"}, {"title": "1978年:阿什顿·库彻，美国演员", "year": "1978"}, {"title": "1979年:小雪，香港歌手、演员", "year": "1979"}, {"title": "1980年:李贞贤，韩国女演员", "year": "1980"}, {"title": "1982年:向井理，日本男演员", "year": "1982"}, {"title": "1983年:克里斯蒂安·克莱恩，奥地利一级方程式赛车运动员", "year": "1983"}, {"title": "1986年:孔连顺，中国男演员", "year": "1986"}, {"title": "1988年:加护亚依，日本女歌手，前早安少女组成员", "year": "1988"}, {"title": "1990年:华晨宇，中国男歌手", "year": "1990"}, {"title": "1990年:Jacksepticeye，爱尔兰YouTuber", "year": "1990"}, {"title": "1990年:詹卢卡·拉帕杜拉，秘鲁足球运动员", "year": "1990"}, {"title": "1992年:矢岛舞美，日本女性组合℃-ute队长", "year": "1992"}, {"title": "1993年:斯里坎特·基达姆比，印度羽球选手", "year": "1993"}, {"title": "1994年:杨宝贝，马来西亚Youtuber", "year": "1994"}, {"title": "1994年:金振焕，韩国男子偶像团体iKON成员", "year": "1994"}, {"title": "1995年:何紫慧，香港女歌手", "year": "1995"}, {"title": "1996年:伊波杏树，日本女声优", "year": "1996"}, {"title": "1996年:萩原舞，日本女性组合℃-ute成员", "year": "1996"}, {"title": "1996年:皮埃尔·盖斯利，法国一级方程式赛车车手", "year": "1996"}, {"title": "1997年:朴昭英，韩国女演员", "year": "1997"}, {"title": "1998年:王净，台湾女艺人、女作家", "year": "1998"}], "name": "出生", "id": "2"}, {"lists": [{"title": "199年:吕布，三国时期名将", "year": "199"}, {"title": "318年:晋愍帝司马邺，字彦旗，西晋的第四任也是最后一任皇帝。（300年出生）", "year": "318"}, {"title": "1799年:爱新觉罗弘历，清朝乾隆皇帝（1711年出生）", "year": "1799"}, {"title": "1862年:普罗斯珀·梅尼埃，法国医学家（1799年出生）", "year": "1862"}, {"title": "1896年:威廉·海登·英格利希，美国印第安纳州联邦众议员（1822年出生）", "year": "1896"}, {"title": "1931年:柔石（1902年出生）、胡也频（1903年出生）、李伟森（1903年出生）、冯铿（1907年出生）、殷夫（1909年出生），左联五烈士", "year": "1931"}, {"title": "1944年:马本斋，八路军将领（1902年出生）", "year": "1944"}, {"title": "1965年:铎尔孟，法国汉学家，《红楼梦》法文全译本审校者（1881年出生）", "year": "1965"}, {"title": "1965年:李海泉，香港粤剧演员，李小龙之父（1901年出生）", "year": "1965"}, {"title": "1974年:竺可桢，中国地理学家（1890年出生）", "year": "1974"}, {"title": "1979年:苏振华，中国共产党中央政治局委员、中国人民解放军上将（1912年出生）", "year": "1979"}, {"title": "1999年:胡笙·宾·塔拉勒，约旦国王（1935年出生）", "year": "1999"}, {"title": "2003年:安德烈·科林巴，中非政治人物，第4任中非共和国总统（1936年出生）", "year": "2003"}, {"title": "2007年:陈炜恒，澳门文化界人士（1962年出生）", "year": "2007"}, {"title": "2011年:陈蕉琴，香港女性企业家和慈善家（1915年出生）", "year": "2011"}, {"title": "2013年:李可，中国著名中医学家（1930年出生）", "year": "2013"}, {"title": "2020年:高秀贞，韩国女演员（1995年出生）", "year": "2020"}, {"title": "2020年:李文亮，曝光2019冠状病毒病疫情的武汉医生之一（1985年出生）", "year": "2020"}], "name": "逝世", "id": "3"}], "month": 2, "day": 7}