{"res": [{"lists": [{"title": "303年:圣乔治日，相传当天罗马骑兵军官圣乔治因试图阻止罗马皇帝戴克里先对基督徒的迫害，而被砍头处死。", "year": "303"}, {"title": "1348年:英国国王爱德华三世在圣乔治日宣布正式成立嘉德骑士团。", "year": "1348"}, {"title": "1661年:查理二世在威斯敏斯特教堂加冕成为英格兰、苏格兰和爱尔兰国王。", "year": "1661"}, {"title": "1732年:台湾发生以吴福生为首的民变，即吴福生事件。", "year": "1732"}, {"title": "1827年:爱尔兰数学家、物理学家哈密顿发表论文《光线系统理论》，建立了光学的数学理论。", "year": "1827"}, {"title": "1853年:俄国占领库页岛。", "year": "1853"}, {"title": "1873年:荷兰向亚齐开战。", "year": "1873"}, {"title": "1875年:清廷任命左宗棠为钦差大臣，督办新疆军务。", "year": "1875"}, {"title": "1895年:三国干涉还辽:在俄罗斯、德国和法国的干涉下，日本将《马关条约》中清廷割让的辽东半岛“归还”中国。", "year": "1895"}, {"title": "1910年:汪精卫等谋刺清朝摄政王载沣未遂被捕。", "year": "1910"}, {"title": "1920年:首届土耳其大国民议会在安卡拉召开，以凯末尔为首的临时政府成立。", "year": "1920"}, {"title": "1945年:中国共产党第七次全国代表大会在陕西延安召开。", "year": "1945"}, {"title": "1949年:第二次国共内战:中国人民解放军在渡江战役中占领中华民国首都南京。", "year": "1949"}, {"title": "1949年:中国人民解放军海军在江苏泰州白马庙成立。", "year": "1949"}, {"title": "1975年:锡金被并入印度。", "year": "1975"}, {"title": "1975年:越南战争:越南共和国政府总辞职，美国承认战争已失败。一星期后越共攻陷西贡，南越灭亡。", "year": "1975"}, {"title": "1982年:美国基韦斯特市市长宣布佛罗里达群岛从美国独立，建立海螺共和国，并在一分钟后向美国海军投降。", "year": "1982"}, {"title": "1990年:尼泊尔警察骚乱。", "year": "1990"}, {"title": "1993年:俄罗斯总统叶利钦公布新宪法草案。", "year": "1993"}, {"title": "2001年:一批支持车臣独立的枪手攻入土耳其伊斯坦布尔一间酒店胁持人质，最终被镇压。", "year": "2001"}, {"title": "2003年:北京由于SARS疫情而关闭所有学校两周。", "year": "2003"}, {"title": "2003年:香港警务处水警总区的小艇队与反走私特遣队合并成为小艇分区。", "year": "2003"}, {"title": "2005年:第一部YouTube影片上传，标题为“我在动物园”（Me at the zoo）。", "year": "2005"}, {"title": "2008年:赛德克族于2008年4月23日正式成为第十四个台湾原住民族。", "year": "2008"}, {"title": "2009年:美国雨燕卫星探测到GRB 090423所发射的伽玛射线暴，这是当时太空探测历史上所测得最为遥远的伽玛射线纪录。", "year": "2009"}, {"title": "2018年:加拿大多伦多客货车撞向人群，增至10人死亡，15人受伤。", "year": "2018"}, {"title": "2018年:英国剑桥公爵夫人凯瑟琳（Kate Middleton）周一诞下小王子。", "year": "2018"}], "name": "大事记", "id": "1"}, {"lists": [{"title": "1564年:莎士比亚，英国剧作家。（1616年逝世）", "year": "1564"}, {"title": "1775年:约瑟夫·玛罗德·威廉·特纳，英国画家。", "year": "1775"}, {"title": "1791年:詹姆斯·布坎南，美国第15任总统。（1868年逝世）", "year": "1791"}, {"title": "1794年:魏源，中国思想家、文学家。（1856年逝世）", "year": "1794"}, {"title": "1823年:阿卜杜勒-迈吉德一世，奥斯曼帝国苏丹。（1861年逝世）", "year": "1823"}, {"title": "1858年:普朗克，德国物理学家。（1947年逝世）", "year": "1858"}, {"title": "1875年:上村松园，日本胶彩画女画家。（1949年逝世）", "year": "1875"}, {"title": "1877年:廖仲恺，中国政治家。（1925年逝世）", "year": "1877"}, {"title": "1891年:普罗柯菲耶夫，苏联作曲家。（1953年逝世）", "year": "1891"}, {"title": "1899年:弗拉基米尔·纳博科夫，俄国作家。（1977年逝世）", "year": "1899"}, {"title": "1902年:哈尔多尔·拉克斯内斯，冰岛作家，1955年诺贝尔文学奖得主。（1998年逝世）", "year": "1902"}, {"title": "1928年:秀兰·邓波儿，美国电影明星，一款无酒精鸡尾酒以她的名字命名。（2014年逝世）", "year": "1928"}, {"title": "1939年:梁智鸿，香港医学界、政界人物。", "year": "1939"}, {"title": "1945年:李焯芬，香港大学教授、学者。", "year": "1945"}, {"title": "1954年:麦可·摩尔，美国纪录片导演。", "year": "1954"}, {"title": "1957年:川井宪次，日本作曲家。", "year": "1957"}, {"title": "1960年:凡莱丽·柏帝内，美国演员", "year": "1960"}, {"title": "1961年:周正毅，香港企业家。", "year": "1961"}, {"title": "1962年:约翰·汉纳，苏格兰演员", "year": "1962"}, {"title": "1963年:梁致盈，香港配音员（2001年逝世）", "year": "1963"}, {"title": "1968年:阿伊莎·宾特·侯赛因，约旦公主。", "year": "1968"}, {"title": "1969年:曼努吉·巴帕依，印度演员", "year": "1969"}, {"title": "1970年:乔宝宝，香港外藉艺员。", "year": "1970"}, {"title": "1970年:阿部サダヲ，日本演员。", "year": "1970"}, {"title": "1976年:森山直太朗，日本歌手。", "year": "1976"}, {"title": "1977年:约翰·希南，美国演员、Hip-Hop歌手、职业摔角选手。", "year": "1977"}, {"title": "1977年:约翰·奥利弗，美国名嘴", "year": "1977"}, {"title": "1977年:凯尔朋·苏雷什·默迪，美国演员", "year": "1977"}, {"title": "1979年:周苏红，中国女排队员", "year": "1979"}, {"title": "1979年:洁米·金，美国演员", "year": "1979"}, {"title": "1982年:Hiroyuki，日本漫画家。", "year": "1982"}, {"title": "1984年:杰西·李·索弗，美国演员", "year": "1984"}, {"title": "1986年:谢茜嘉·史谭，加拿大女性模特儿。", "year": "1986"}, {"title": "1986年:张芯瑜，台湾女歌手。", "year": "1986"}, {"title": "1988年:严爵，台湾创作歌手。", "year": "1988"}, {"title": "1989年:瓦伊迪索娃，捷克网球运动员。", "year": "1989"}, {"title": "1995年:吉吉·哈蒂德，美国女性模特儿。", "year": "1995"}, {"title": "1995年:尹芮珠，韩国女演员。", "year": "1995"}, {"title": "1999年:孙彩瑛，韩国女子偶像团体TWICE成员。", "year": "1999"}, {"title": "2000年:Jeno，韩国男子偶像团体NCT成员。", "year": "2000"}, {"title": "2018年:路易王子，英国王子。", "year": "2018"}], "name": "出生", "id": "2"}, {"lists": [{"title": "1200年:朱熹，中国思想家、文学家（生于1130年）", "year": "1200"}, {"title": "1616年:印卡·加西拉索·德拉维加，麦士蒂索人作家（生于1539年）", "year": "1616"}, {"title": "1616年:莎士比亚，英国剧作家。（儒略历，生于1564年）", "year": "1616"}, {"title": "1616年:塞万提斯，西班牙小说家、剧作家、诗人（生于1547年）", "year": "1616"}, {"title": "1850年:威廉·华兹华斯，英国浪漫主义诗人（生于1770年）", "year": "1850"}, {"title": "1896年:武训，乞讨财物兴办义学的奇人（生于1838年）", "year": "1896"}, {"title": "1946年:夏丏尊，中国作家，教育家。（生于1886年）", "year": "1946"}, {"title": "1969年:郑君里，中国电影、话剧艺术家。（生于1911年）", "year": "1969"}, {"title": "1989年:胡蝶，中国早期电影明星。（生于1907年）", "year": "1989"}, {"title": "1996年:P·L·卓华斯，英国作家，《玛丽·包萍》作者。（生于1899年）", "year": "1996"}, {"title": "1997年:黄胄，中国国画家。（生于1925年）", "year": "1997"}, {"title": "2005年:约翰·米尔斯爵士，英国电影演员。（生于1908年）", "year": "2005"}, {"title": "2007年:黄秉干，香港事务律师。（生于1928年）", "year": "2007"}, {"title": "2007年:叶利钦，俄罗斯前总统。（生于1931年）", "year": "2007"}, {"title": "2009年:林尚义，前香港足球员及香港电视足球评述员。（生于1934年）", "year": "2009"}, {"title": "2013年:穆罕默德·奥马尔，阿富汗伊斯兰教组织塔利班的领导人。（生于1960年）", "year": "2013"}, {"title": "2017年:曾守明，香港无线电视演员、特技人、皇家香港军团（义勇军）军人。(生于1958年)", "year": "2017"}], "name": "逝世", "id": "3"}], "month": 4, "day": 23}